{
  "fetched_at": "2025-12-25T20:46:40.568434",
  "table_name": "resident_absences",
  "table_id": "tblQl3C95pOUE6FOP",
  "record_count": 107,
  "records": [
    {
      "id": "rec0sG1Ka9xHEcWn0",
      "createdTime": "2025-08-27T04:12:01.000Z",
      "fields": {
        "absenceRequest": "TRUE - TRUE -  - 2025-08-01T00:00:00.000Z - 2025-08-05T00:00:00.000Z",
        "absenceId": "rec0sG1Ka9xHEcWn0",
        "absenceStart": "2025-08-01",
        "absenceEnd": "2025-08-05",
        "absenceDuration": 5,
        "absenceApprovedResidency": true,
        "absenceApprovedArmy": true,
        "blockNumber": [
          "recba9vit0iwjDvyd"
        ],
        "comments": "Leave identified as missing per FAC-CORE-01 FAC-CORE-01 email from July 25, 2025"
      }
    },
    {
      "id": "rec1CYX9NKgU2U4LH",
      "createdTime": "2025-08-26T22:43:01.000Z",
      "fields": {
        "absenceRequest": "TRUE - TRUE - PGY1-05 - 2026-04-20T00:00:00.000Z - 2026-04-27T00:00:00.000Z",
        "resident": [
          "recdJZeXQjXmXhP4Q"
        ],
        "absenceId": "rec1CYX9NKgU2U4LH",
        "postGraduateYear": [
          "recBFlKB0nKMu8uqX"
        ],
        "residentId": [
          "recdJZeXQjXmXhP4Q"
        ],
        "absenceStart": "2026-04-20",
        "absenceEnd": "2026-04-27",
        "absenceDuration": 8,
        "absenceApprovedResidency": true,
        "absenceApprovedArmy": true,
        "blockNumber": [
          "recukCPK15uxoCGtJ"
        ],
        "comments": "Imported from Excel: April 20 - 27 (Block 11)"
      }
    },
    {
      "id": "rec1w39jdIOCLCvYI",
      "createdTime": "2025-08-26T22:42:43.000Z",
      "fields": {
        "absenceRequest": "TRUE - TRUE - PGY1-05 - 2025-12-21T00:00:00.000Z - 2025-12-28T00:00:00.000Z",
        "resident": [
          "recdJZeXQjXmXhP4Q"
        ],
        "absenceId": "rec1w39jdIOCLCvYI",
        "postGraduateYear": [
          "recBFlKB0nKMu8uqX"
        ],
        "residentId": [
          "recdJZeXQjXmXhP4Q"
        ],
        "absenceStart": "2025-12-21",
        "absenceEnd": "2025-12-28",
        "absenceDuration": 8,
        "absenceApprovedResidency": true,
        "absenceApprovedArmy": true,
        "blockNumber": [
          "rec4QEhUx2W3VpbJg"
        ],
        "comments": "Imported from Excel: Dec 21 - 28 (Block 7)"
      }
    },
    {
      "id": "rec23c6YeLTg2Chmt",
      "createdTime": "2025-08-06T22:06:19.000Z",
      "fields": {
        "absenceRequest": "TRUE - TRUE - PGY2-01 - 2025-11-24T00:00:00.000Z - 2025-11-26T00:00:00.000Z",
        "resident": [
          "rec3TityYwwXKG80J"
        ],
        "absenceId": "rec23c6YeLTg2Chmt",
        "postGraduateYear": [
          "rechgRuK16I8kTScb"
        ],
        "residentId": [
          "rec3TityYwwXKG80J"
        ],
        "absenceStart": "2025-11-24",
        "absenceEnd": "2025-11-26",
        "absenceDuration": 3,
        "absenceApprovedResidency": true,
        "absenceApprovedArmy": true,
        "blockNumber": [
          "recheHoNFIphdOOkc"
        ],
        "comments": "Leave"
      }
    },
    {
      "id": "rec2iqlfOaJuWM24a",
      "createdTime": "2025-05-29T02:17:24.000Z",
      "fields": {
        "absenceRequest": "TRUE - TRUE - PGY3-03 - 2025-07-26T00:00:00.000Z - 2025-07-31T00:00:00.000Z",
        "resident": [
          "rec8tD8mJTRq51ewo"
        ],
        "absenceId": "rec2iqlfOaJuWM24a",
        "postGraduateYear": [
          "recEWQHvAnrsTqGHO"
        ],
        "residentId": [
          "rec8tD8mJTRq51ewo"
        ],
        "absenceStart": "2025-07-26",
        "absenceEnd": "2025-07-31",
        "absenceDuration": 6,
        "absenceApprovedResidency": true,
        "absenceApprovedArmy": true,
        "blockNumber": [
          "recyCXLCOdygmwkaB",
          "recba9vit0iwjDvyd"
        ],
        "comments": "Leave"
      }
    },
    {
      "id": "rec2qciaqpEHDSl8o",
      "createdTime": "2025-08-22T20:40:02.000Z",
      "fields": {
        "absenceRequest": "TRUE - TRUE - PGY1-05 - 2025-10-08T00:00:00.000Z - 2025-10-09T00:00:00.000Z",
        "resident": [
          "recdJZeXQjXmXhP4Q"
        ],
        "absenceId": "rec2qciaqpEHDSl8o",
        "postGraduateYear": [
          "recBFlKB0nKMu8uqX"
        ],
        "residentId": [
          "recdJZeXQjXmXhP4Q"
        ],
        "absenceStart": "2025-10-08",
        "absenceEnd": "2025-10-09",
        "absenceDuration": 2,
        "absenceApprovedResidency": true,
        "absenceApprovedArmy": true,
        "blockNumber": [
          "recxSe9VbRMwt4DqQ"
        ],
        "comments": "COMLEX Level 3 (Day 1\u20132) during IM wards; coordinate coverage."
      }
    },
    {
      "id": "rec3norCmvbzi7dJr",
      "createdTime": "2025-08-06T22:10:21.000Z",
      "fields": {
        "absenceRequest": "TRUE - TRUE - PGY3-04 - 2025-10-09T00:00:00.000Z - 2025-10-12T00:00:00.000Z",
        "resident": [
          "recGZP0N9JXnYK2tq"
        ],
        "absenceId": "rec3norCmvbzi7dJr",
        "postGraduateYear": [
          "recEWQHvAnrsTqGHO"
        ],
        "residentId": [
          "recGZP0N9JXnYK2tq"
        ],
        "absenceStart": "2025-10-09",
        "absenceEnd": "2025-10-12",
        "absenceDuration": 4,
        "absenceApprovedResidency": true,
        "absenceApprovedArmy": true,
        "blockNumber": [
          "recxSe9VbRMwt4DqQ"
        ],
        "comments": "Leave"
      }
    },
    {
      "id": "rec3sp4f1TFMohvCb",
      "createdTime": "2025-08-26T22:48:51.000Z",
      "fields": {
        "absenceRequest": "TRUE - TRUE - PGY3-05 - 2025-08-18T00:00:00.000Z - 2025-08-24T00:00:00.000Z",
        "resident": [
          "recfCEd4ydvmWPMbq"
        ],
        "absenceId": "rec3sp4f1TFMohvCb",
        "postGraduateYear": [
          "recEWQHvAnrsTqGHO"
        ],
        "residentId": [
          "recfCEd4ydvmWPMbq"
        ],
        "absenceStart": "2025-08-18",
        "absenceEnd": "2025-08-24",
        "absenceDuration": 7,
        "absenceApprovedResidency": true,
        "absenceApprovedArmy": true,
        "blockNumber": [
          "recba9vit0iwjDvyd"
        ],
        "comments": "Imported from Excel: Aug 18 - 24 (Block 2)"
      }
    },
    {
      "id": "rec4CcqVVNRLKdkt6",
      "createdTime": "2025-08-26T22:41:57.000Z",
      "fields": {
        "absenceRequest": "TRUE - TRUE - PGY1-03 - 2025-10-27T00:00:00.000Z - 2025-11-02T00:00:00.000Z",
        "resident": [
          "rec8sCH92dmDNq0Jy"
        ],
        "absenceId": "rec4CcqVVNRLKdkt6",
        "postGraduateYear": [
          "recBFlKB0nKMu8uqX"
        ],
        "residentId": [
          "rec8sCH92dmDNq0Jy"
        ],
        "absenceStart": "2025-10-27",
        "absenceEnd": "2025-11-02",
        "absenceDuration": 7,
        "absenceApprovedResidency": true,
        "absenceApprovedArmy": true,
        "blockNumber": [
          "reciDYU7hTsmjgAaT"
        ],
        "comments": "Imported from Excel: Oct 27 - Nov 2 (Block 5)"
      }
    },
    {
      "id": "rec5ehVuAn5gluZGj",
      "createdTime": "2025-05-29T02:15:24.000Z",
      "fields": {
        "absenceRequest": "TRUE - TRUE - PGY3-04 - 2025-07-23T00:00:00.000Z - 2025-07-30T00:00:00.000Z",
        "resident": [
          "recGZP0N9JXnYK2tq"
        ],
        "absenceId": "rec5ehVuAn5gluZGj",
        "postGraduateYear": [
          "recEWQHvAnrsTqGHO"
        ],
        "residentId": [
          "recGZP0N9JXnYK2tq"
        ],
        "absenceStart": "2025-07-23",
        "absenceEnd": "2025-07-30",
        "absenceDuration": 8,
        "absenceApprovedResidency": true,
        "absenceApprovedArmy": true,
        "blockNumber": [
          "recyCXLCOdygmwkaB"
        ],
        "comments": "Leave"
      }
    },
    {
      "id": "rec76XnEkWEti9Yto",
      "createdTime": "2025-08-26T22:35:56.000Z",
      "fields": {
        "absenceRequest": "TRUE - TRUE - PGY1-01 - 2025-10-05T00:00:00.000Z - 2025-10-11T00:00:00.000Z",
        "resident": [
          "rec5jcPQWWX9phYCc"
        ],
        "absenceId": "rec76XnEkWEti9Yto",
        "postGraduateYear": [
          "recBFlKB0nKMu8uqX"
        ],
        "residentId": [
          "rec5jcPQWWX9phYCc"
        ],
        "absenceStart": "2025-10-05",
        "absenceEnd": "2025-10-11",
        "absenceDuration": 7,
        "absenceApprovedResidency": true,
        "absenceApprovedArmy": true,
        "blockNumber": [
          "recxSe9VbRMwt4DqQ"
        ],
        "comments": "Imported from Excel: Oct 5 - 11 (Block 4)"
      }
    },
    {
      "id": "rec7hu3KvcsZ7y0xa",
      "createdTime": "2025-08-26T22:48:03.000Z",
      "fields": {
        "absenceRequest": "TRUE - TRUE - PGY3-03 - 2026-05-25T00:00:00.000Z - 2026-05-26T00:00:00.000Z",
        "resident": [
          "rec8tD8mJTRq51ewo"
        ],
        "absenceId": "rec7hu3KvcsZ7y0xa",
        "postGraduateYear": [
          "recEWQHvAnrsTqGHO"
        ],
        "residentId": [
          "rec8tD8mJTRq51ewo"
        ],
        "absenceStart": "2026-05-25",
        "absenceEnd": "2026-05-26",
        "absenceDuration": 2,
        "absenceApprovedResidency": true,
        "absenceApprovedArmy": true,
        "blockNumber": [
          "rectoByFjGEhCHnP0"
        ],
        "comments": "Imported from Excel: May 25 - 26"
      }
    },
    {
      "id": "recA2nYLhaHinXhf1",
      "createdTime": "2025-07-23T19:53:27.000Z",
      "fields": {
        "absenceRequest": "TRUE - TRUE - PGY2-01 - 2025-09-15T00:00:00.000Z - 2025-09-19T00:00:00.000Z",
        "resident": [
          "rec3TityYwwXKG80J"
        ],
        "absenceId": "recA2nYLhaHinXhf1",
        "postGraduateYear": [
          "rechgRuK16I8kTScb"
        ],
        "residentId": [
          "rec3TityYwwXKG80J"
        ],
        "absenceStart": "2025-09-15",
        "absenceEnd": "2025-09-19",
        "absenceDuration": 5,
        "absenceApprovedResidency": true,
        "absenceApprovedArmy": true,
        "blockNumber": [
          "recldLCwxBq8qUpNY"
        ],
        "comments": "Leave"
      }
    },
    {
      "id": "recAeBme1s1Ao8VNF",
      "createdTime": "2025-07-16T23:40:31.000Z",
      "fields": {
        "absenceRequest": "TRUE - TRUE - PGY2-02 - 2025-07-31T00:00:00.000Z - 2025-08-06T00:00:00.000Z",
        "resident": [
          "recAtFCfEO8EjeJXh"
        ],
        "absenceId": "recAeBme1s1Ao8VNF",
        "postGraduateYear": [
          "rechgRuK16I8kTScb"
        ],
        "residentId": [
          "recAtFCfEO8EjeJXh"
        ],
        "absenceStart": "2025-07-31",
        "absenceEnd": "2025-08-06",
        "absenceDuration": 7,
        "absenceApprovedResidency": true,
        "absenceApprovedArmy": true,
        "blockNumber": [
          "recba9vit0iwjDvyd"
        ],
        "comments": "Leave"
      }
    },
    {
      "id": "recBD7Wnm7ZX7UAYP",
      "createdTime": "2025-08-26T22:36:05.000Z",
      "fields": {
        "absenceRequest": "TRUE - TRUE - PGY1-01 - 2025-12-07T00:00:00.000Z - 2025-12-13T00:00:00.000Z",
        "resident": [
          "rec5jcPQWWX9phYCc"
        ],
        "absenceId": "recBD7Wnm7ZX7UAYP",
        "postGraduateYear": [
          "recBFlKB0nKMu8uqX"
        ],
        "residentId": [
          "rec5jcPQWWX9phYCc"
        ],
        "absenceStart": "2025-12-07",
        "absenceEnd": "2025-12-13",
        "absenceDuration": 7,
        "absenceApprovedResidency": true,
        "absenceApprovedArmy": true,
        "blockNumber": [
          "recheHoNFIphdOOkc"
        ],
        "comments": "Imported from Excel: Dec 7- 13 (Block 6)"
      }
    },
    {
      "id": "recBZ7hFMVHfPzQfE",
      "createdTime": "2025-08-26T22:46:34.000Z",
      "fields": {
        "absenceRequest": "TRUE - TRUE - PGY2-01 - 2026-05-23T00:00:00.000Z - 2026-05-26T00:00:00.000Z",
        "resident": [
          "rec3TityYwwXKG80J"
        ],
        "absenceId": "recBZ7hFMVHfPzQfE",
        "postGraduateYear": [
          "rechgRuK16I8kTScb"
        ],
        "residentId": [
          "rec3TityYwwXKG80J"
        ],
        "absenceStart": "2026-05-23",
        "absenceEnd": "2026-05-26",
        "absenceDuration": 4,
        "absenceApprovedResidency": true,
        "absenceApprovedArmy": true,
        "blockNumber": [
          "rectoByFjGEhCHnP0"
        ],
        "comments": "Imported from Excel: May 23 - 26 (Block 12)"
      }
    },
    {
      "id": "recBs2sCuKmCmpUOs",
      "createdTime": "2025-08-06T22:00:57.000Z",
      "fields": {
        "absenceRequest": "TRUE - TRUE - PGY1-02 - 2025-09-20T00:00:00.000Z - 2025-09-26T00:00:00.000Z",
        "resident": [
          "rec6w0pOz3z54OaNH"
        ],
        "absenceId": "recBs2sCuKmCmpUOs",
        "postGraduateYear": [
          "recBFlKB0nKMu8uqX"
        ],
        "residentId": [
          "rec6w0pOz3z54OaNH"
        ],
        "absenceStart": "2025-09-20",
        "absenceEnd": "2025-09-26",
        "absenceDuration": 7,
        "absenceApprovedResidency": true,
        "absenceApprovedArmy": true,
        "blockNumber": [
          "recxSe9VbRMwt4DqQ"
        ],
        "comments": "Leave"
      }
    },
    {
      "id": "recByNj61SPbrz4Yq",
      "createdTime": "2025-05-29T02:11:51.000Z",
      "fields": {
        "absenceRequest": "TRUE - TRUE - PGY2-05 - 2025-07-09T00:00:00.000Z - 2025-07-13T00:00:00.000Z",
        "resident": [
          "recjkLHNGSlRaZA0R"
        ],
        "absenceId": "recByNj61SPbrz4Yq",
        "postGraduateYear": [
          "rechgRuK16I8kTScb"
        ],
        "residentId": [
          "recjkLHNGSlRaZA0R"
        ],
        "absenceStart": "2025-07-09",
        "absenceEnd": "2025-07-13",
        "absenceDuration": 5,
        "absenceApprovedResidency": true,
        "absenceApprovedArmy": true,
        "blockNumber": [
          "recyCXLCOdygmwkaB"
        ],
        "comments": "Leave"
      }
    },
    {
      "id": "recC5tSZh3MIVEeT3",
      "createdTime": "2025-08-26T22:41:23.000Z",
      "fields": {
        "absenceRequest": "TRUE - TRUE - PGY1-02 - 2025-09-20T00:00:00.000Z - 2025-09-26T00:00:00.000Z",
        "resident": [
          "rec6w0pOz3z54OaNH"
        ],
        "absenceId": "recC5tSZh3MIVEeT3",
        "postGraduateYear": [
          "recBFlKB0nKMu8uqX"
        ],
        "residentId": [
          "rec6w0pOz3z54OaNH"
        ],
        "absenceStart": "2025-09-20",
        "absenceEnd": "2025-09-26",
        "absenceDuration": 7,
        "absenceApprovedResidency": true,
        "absenceApprovedArmy": true,
        "blockNumber": [
          "recxSe9VbRMwt4DqQ"
        ],
        "comments": "Imported from Excel: Sep 20 - 26 (Block 4)"
      }
    },
    {
      "id": "recC7I1td2ZtcaSfi",
      "createdTime": "2025-08-26T22:37:11.000Z",
      "fields": {
        "absenceRequest": "TRUE - TRUE - PGY1-06 - 2025-09-01T00:00:00.000Z - 2025-09-07T00:00:00.000Z",
        "resident": [
          "recsi4ZOjSvEoVT7m"
        ],
        "absenceId": "recC7I1td2ZtcaSfi",
        "postGraduateYear": [
          "recBFlKB0nKMu8uqX"
        ],
        "residentId": [
          "recsi4ZOjSvEoVT7m"
        ],
        "absenceStart": "2025-09-01",
        "absenceEnd": "2025-09-07",
        "absenceDuration": 7,
        "absenceApprovedResidency": true,
        "absenceApprovedArmy": true,
        "blockNumber": [
          "recldLCwxBq8qUpNY"
        ],
        "comments": "Imported from Excel: Sept 1 - 7 (Block 3)"
      }
    },
    {
      "id": "recC9Uf6gj8ZyXifE",
      "createdTime": "2025-08-06T22:01:26.000Z",
      "fields": {
        "absenceRequest": "TRUE - TRUE - PGY1-03 - 2025-10-27T00:00:00.000Z - 2025-11-02T00:00:00.000Z",
        "resident": [
          "rec8sCH92dmDNq0Jy"
        ],
        "absenceId": "recC9Uf6gj8ZyXifE",
        "postGraduateYear": [
          "recBFlKB0nKMu8uqX"
        ],
        "residentId": [
          "rec8sCH92dmDNq0Jy"
        ],
        "absenceStart": "2025-10-27",
        "absenceEnd": "2025-11-02",
        "absenceDuration": 7,
        "absenceApprovedResidency": true,
        "absenceApprovedArmy": true,
        "blockNumber": [
          "reciDYU7hTsmjgAaT"
        ],
        "comments": "Leave"
      }
    },
    {
      "id": "recCNeyAfheBecJ4o",
      "createdTime": "2025-08-26T22:47:22.000Z",
      "fields": {
        "absenceRequest": "TRUE - TRUE - PGY3-02 - 2025-07-07T00:00:00.000Z - 2025-07-09T00:00:00.000Z",
        "resident": [
          "rec72mJXy7UnA5R1n"
        ],
        "absenceId": "recCNeyAfheBecJ4o",
        "postGraduateYear": [
          "recEWQHvAnrsTqGHO"
        ],
        "residentId": [
          "rec72mJXy7UnA5R1n"
        ],
        "absenceStart": "2025-07-07",
        "absenceEnd": "2025-07-09",
        "absenceDuration": 3,
        "absenceApprovedResidency": true,
        "absenceApprovedArmy": true,
        "blockNumber": [
          "recyCXLCOdygmwkaB"
        ],
        "comments": "Imported from Excel: July 7-9 (Block 1)"
      }
    },
    {
      "id": "recDOqLe9fxDPY6iU",
      "createdTime": "2025-09-18T22:15:16.000Z",
      "fields": {
        "absenceRequest": "TRUE - TRUE - PGY3-01 - 2026-04-09T00:00:00.000Z - 2026-04-15T00:00:00.000Z",
        "resident": [
          "rec5HLr3R4qE79jK0"
        ],
        "absenceId": "recDOqLe9fxDPY6iU",
        "postGraduateYear": [
          "recEWQHvAnrsTqGHO"
        ],
        "residentId": [
          "rec5HLr3R4qE79jK0"
        ],
        "absenceStart": "2026-04-09",
        "absenceEnd": "2026-04-15",
        "absenceDuration": 7,
        "absenceApprovedResidency": true,
        "absenceApprovedArmy": true,
        "blockNumber": [
          "recukCPK15uxoCGtJ"
        ],
        "comments": "Leave"
      }
    },
    {
      "id": "recDq7wlbD7iYr6L1",
      "createdTime": "2025-08-26T22:41:13.000Z",
      "fields": {
        "absenceRequest": "TRUE - TRUE - PGY1-06 - 2026-06-04T00:00:00.000Z - 2026-06-07T00:00:00.000Z",
        "resident": [
          "recsi4ZOjSvEoVT7m"
        ],
        "absenceId": "recDq7wlbD7iYr6L1",
        "postGraduateYear": [
          "recBFlKB0nKMu8uqX"
        ],
        "residentId": [
          "recsi4ZOjSvEoVT7m"
        ],
        "absenceStart": "2026-06-04",
        "absenceEnd": "2026-06-07",
        "absenceDuration": 4,
        "absenceApprovedResidency": true,
        "absenceApprovedArmy": true,
        "blockNumber": [
          "recWQEZ1WZ8lvXReP"
        ],
        "comments": "Imported from Excel: June 4 - 7 (Block 13)"
      }
    },
    {
      "id": "recE0mInrvssbMXv6",
      "createdTime": "2025-05-29T02:06:29.000Z",
      "fields": {
        "absenceRequest": "TRUE - TRUE - PGY2-04 - 2025-07-06T00:00:00.000Z - 2025-07-12T00:00:00.000Z",
        "resident": [
          "recSyteEOxDCJUCM1"
        ],
        "absenceId": "recE0mInrvssbMXv6",
        "postGraduateYear": [
          "rechgRuK16I8kTScb"
        ],
        "residentId": [
          "recSyteEOxDCJUCM1"
        ],
        "absenceStart": "2025-07-06",
        "absenceEnd": "2025-07-12",
        "absenceDuration": 7,
        "absenceApprovedResidency": true,
        "absenceApprovedArmy": true,
        "blockNumber": [
          "recyCXLCOdygmwkaB"
        ],
        "comments": "Leave"
      }
    },
    {
      "id": "recEPHExEn1YGWcI1",
      "createdTime": "2025-08-26T22:37:50.000Z",
      "fields": {
        "absenceRequest": "TRUE - TRUE - PGY1-06 - 2025-12-29T00:00:00.000Z - 2026-01-04T00:00:00.000Z",
        "resident": [
          "recsi4ZOjSvEoVT7m"
        ],
        "absenceId": "recEPHExEn1YGWcI1",
        "postGraduateYear": [
          "recBFlKB0nKMu8uqX"
        ],
        "residentId": [
          "recsi4ZOjSvEoVT7m"
        ],
        "absenceStart": "2025-12-29",
        "absenceEnd": "2026-01-04",
        "absenceDuration": 7,
        "absenceApprovedResidency": true,
        "absenceApprovedArmy": true,
        "blockNumber": [
          "rec4QEhUx2W3VpbJg"
        ],
        "comments": "Imported from Excel: Dec 29 - Jan 4 (Block 7)"
      }
    },
    {
      "id": "recFKkWSG1WhxAcm2",
      "createdTime": "2025-04-30T20:35:33.000Z",
      "fields": {
        "absenceRequest": "TRUE - TRUE - PGY2-06 - 2025-07-01T00:00:00.000Z - 2025-07-06T00:00:00.000Z",
        "resident": [
          "recyynCFupNGxL9NK"
        ],
        "absenceId": "recFKkWSG1WhxAcm2",
        "postGraduateYear": [
          "rechgRuK16I8kTScb"
        ],
        "residentId": [
          "recyynCFupNGxL9NK"
        ],
        "absenceStart": "2025-07-01",
        "absenceEnd": "2025-07-06",
        "absenceDuration": 6,
        "absenceApprovedResidency": true,
        "absenceApprovedArmy": true,
        "blockNumber": [
          "recyCXLCOdygmwkaB"
        ],
        "comments": "Leave"
      }
    },
    {
      "id": "recFxajyqpMXesv76",
      "createdTime": "2025-06-28T19:53:13.000Z",
      "fields": {
        "absenceRequest": "TRUE - TRUE - PGY2-05 - 2026-02-18T00:00:00.000Z - 2026-02-27T00:00:00.000Z",
        "resident": [
          "recjkLHNGSlRaZA0R"
        ],
        "absenceId": "recFxajyqpMXesv76",
        "postGraduateYear": [
          "rechgRuK16I8kTScb"
        ],
        "residentId": [
          "recjkLHNGSlRaZA0R"
        ],
        "absenceStart": "2026-02-18",
        "absenceEnd": "2026-02-27",
        "absenceDuration": 10,
        "absenceApprovedResidency": true,
        "absenceApprovedArmy": true,
        "blockNumber": [
          "rec9KG7LgejhaAdDP"
        ],
        "comments": "C4"
      }
    },
    {
      "id": "recGHx8z0Ks6zwpIV",
      "createdTime": "2025-08-26T22:45:40.000Z",
      "fields": {
        "absenceRequest": "TRUE - TRUE - PGY2-06 - 2025-10-23T00:00:00.000Z - 2025-10-26T00:00:00.000Z",
        "resident": [
          "recyynCFupNGxL9NK"
        ],
        "absenceId": "recGHx8z0Ks6zwpIV",
        "postGraduateYear": [
          "rechgRuK16I8kTScb"
        ],
        "residentId": [
          "recyynCFupNGxL9NK"
        ],
        "absenceStart": "2025-10-23",
        "absenceEnd": "2025-10-26",
        "absenceDuration": 4,
        "absenceApprovedResidency": true,
        "absenceApprovedArmy": true,
        "blockNumber": [
          "reciDYU7hTsmjgAaT"
        ],
        "comments": "Imported from Excel: Oct 23 - 26 (Block 5)"
      }
    },
    {
      "id": "recGMctzDRFq96kZ3",
      "createdTime": "2025-08-26T22:43:24.000Z",
      "fields": {
        "absenceRequest": "TRUE - TRUE - PGY2-02 - 2025-12-21T00:00:00.000Z - 2025-12-28T00:00:00.000Z",
        "resident": [
          "recAtFCfEO8EjeJXh"
        ],
        "absenceId": "recGMctzDRFq96kZ3",
        "postGraduateYear": [
          "rechgRuK16I8kTScb"
        ],
        "residentId": [
          "recAtFCfEO8EjeJXh"
        ],
        "absenceStart": "2025-12-21",
        "absenceEnd": "2025-12-28",
        "absenceDuration": 8,
        "absenceApprovedResidency": true,
        "absenceApprovedArmy": true,
        "blockNumber": [
          "rec4QEhUx2W3VpbJg"
        ],
        "comments": "Imported from Excel: Dec 21 - 28 (Block 7)"
      }
    },
    {
      "id": "recGMvR9VQ9lAz0QA",
      "createdTime": "2025-08-26T22:48:22.000Z",
      "fields": {
        "absenceRequest": "TRUE - TRUE - PGY3-04 - 2025-08-18T00:00:00.000Z - 2025-08-24T00:00:00.000Z",
        "resident": [
          "recGZP0N9JXnYK2tq"
        ],
        "absenceId": "recGMvR9VQ9lAz0QA",
        "postGraduateYear": [
          "recEWQHvAnrsTqGHO"
        ],
        "residentId": [
          "recGZP0N9JXnYK2tq"
        ],
        "absenceStart": "2025-08-18",
        "absenceEnd": "2025-08-24",
        "absenceDuration": 7,
        "absenceApprovedResidency": true,
        "absenceApprovedArmy": true,
        "blockNumber": [
          "recba9vit0iwjDvyd"
        ],
        "comments": "Imported from Excel: Aug 18-24 (Block 2)"
      }
    },
    {
      "id": "recHCypTL53mMQpC1",
      "createdTime": "2025-08-06T22:04:05.000Z",
      "fields": {
        "absenceRequest": "TRUE - TRUE - PGY1-05 - 2025-10-23T00:00:00.000Z - 2025-10-28T00:00:00.000Z",
        "resident": [
          "recdJZeXQjXmXhP4Q"
        ],
        "absenceId": "recHCypTL53mMQpC1",
        "postGraduateYear": [
          "recBFlKB0nKMu8uqX"
        ],
        "residentId": [
          "recdJZeXQjXmXhP4Q"
        ],
        "absenceStart": "2025-10-23",
        "absenceEnd": "2025-10-28",
        "absenceDuration": 6,
        "absenceApprovedResidency": true,
        "absenceApprovedArmy": true,
        "blockNumber": [
          "reciDYU7hTsmjgAaT"
        ],
        "comments": "Leave"
      }
    },
    {
      "id": "recHKoHEvYH6iIkUL",
      "createdTime": "2025-08-06T22:04:48.000Z",
      "fields": {
        "absenceRequest": "TRUE - TRUE - PGY2-02 - 2025-10-20T00:00:00.000Z - 2025-10-22T00:00:00.000Z",
        "resident": [
          "recAtFCfEO8EjeJXh"
        ],
        "absenceId": "recHKoHEvYH6iIkUL",
        "postGraduateYear": [
          "rechgRuK16I8kTScb"
        ],
        "residentId": [
          "recAtFCfEO8EjeJXh"
        ],
        "absenceStart": "2025-10-20",
        "absenceEnd": "2025-10-22",
        "absenceDuration": 3,
        "absenceApprovedResidency": true,
        "absenceApprovedArmy": true,
        "blockNumber": [
          "recxSe9VbRMwt4DqQ"
        ],
        "comments": "Leave"
      }
    },
    {
      "id": "recHSmiwJdLBlUXOt",
      "createdTime": "2025-08-26T22:41:06.000Z",
      "fields": {
        "absenceRequest": "TRUE - TRUE - PGY1-06 - 2026-02-02T00:00:00.000Z - 2026-02-06T00:00:00.000Z",
        "resident": [
          "recsi4ZOjSvEoVT7m"
        ],
        "absenceId": "recHSmiwJdLBlUXOt",
        "postGraduateYear": [
          "recBFlKB0nKMu8uqX"
        ],
        "residentId": [
          "recsi4ZOjSvEoVT7m"
        ],
        "absenceStart": "2026-02-02",
        "absenceEnd": "2026-02-06",
        "absenceDuration": 5,
        "absenceApprovedResidency": true,
        "absenceApprovedArmy": true,
        "blockNumber": [
          "recO8nXpj7mKdnOC2"
        ],
        "comments": "Imported from Excel: Feb 2- 6 (Block 8)"
      }
    },
    {
      "id": "recI5ueaQlBOZz6ZG",
      "createdTime": "2025-06-28T19:54:30.000Z",
      "fields": {
        "absenceRequest": "TRUE - TRUE - PGY2-01 - 2026-05-13T00:00:00.000Z - 2026-05-22T00:00:00.000Z",
        "resident": [
          "rec3TityYwwXKG80J"
        ],
        "absenceId": "recI5ueaQlBOZz6ZG",
        "postGraduateYear": [
          "rechgRuK16I8kTScb"
        ],
        "residentId": [
          "rec3TityYwwXKG80J"
        ],
        "absenceStart": "2026-05-13",
        "absenceEnd": "2026-05-22",
        "absenceDuration": 10,
        "absenceApprovedResidency": true,
        "absenceApprovedArmy": true,
        "blockNumber": [
          "rectoByFjGEhCHnP0"
        ],
        "comments": "C4"
      }
    },
    {
      "id": "recIC4BC4Gv3W3U99",
      "createdTime": "2025-08-26T22:47:56.000Z",
      "fields": {
        "absenceRequest": "TRUE - TRUE - PGY3-03 - 2026-01-19T00:00:00.000Z - 2026-01-21T00:00:00.000Z",
        "resident": [
          "rec8tD8mJTRq51ewo"
        ],
        "absenceId": "recIC4BC4Gv3W3U99",
        "postGraduateYear": [
          "recEWQHvAnrsTqGHO"
        ],
        "residentId": [
          "rec8tD8mJTRq51ewo"
        ],
        "absenceStart": "2026-01-19",
        "absenceEnd": "2026-01-21",
        "absenceDuration": 3,
        "absenceApprovedResidency": true,
        "absenceApprovedArmy": true,
        "blockNumber": [
          "recO8nXpj7mKdnOC2"
        ],
        "comments": "Imported from Excel: Jan 19 - 21 (Block 8)"
      }
    },
    {
      "id": "recIG9TqWoUUyZTnG",
      "createdTime": "2025-08-26T22:35:17.000Z",
      "fields": {
        "absenceRequest": "TRUE - TRUE - PGY1-04 - 2026-02-08T00:00:00.000Z - 2026-02-11T00:00:00.000Z",
        "resident": [
          "recTstPguvGjy3jlb"
        ],
        "absenceId": "recIG9TqWoUUyZTnG",
        "postGraduateYear": [
          "recBFlKB0nKMu8uqX"
        ],
        "residentId": [
          "recTstPguvGjy3jlb"
        ],
        "absenceStart": "2026-02-08",
        "absenceEnd": "2026-02-11",
        "absenceDuration": 4,
        "absenceApprovedResidency": true,
        "absenceApprovedArmy": true,
        "blockNumber": [
          "recO8nXpj7mKdnOC2"
        ],
        "comments": "Imported from Excel: Feb 8-11 (Block 8)"
      }
    },
    {
      "id": "recJXbVg2QhnDTS0c",
      "createdTime": "2025-08-26T22:46:42.000Z",
      "fields": {
        "absenceRequest": "TRUE - TRUE - PGY2-01 - 2026-06-18T00:00:00.000Z - 2026-06-19T00:00:00.000Z",
        "resident": [
          "rec3TityYwwXKG80J"
        ],
        "absenceId": "recJXbVg2QhnDTS0c",
        "postGraduateYear": [
          "rechgRuK16I8kTScb"
        ],
        "residentId": [
          "rec3TityYwwXKG80J"
        ],
        "absenceStart": "2026-06-18",
        "absenceEnd": "2026-06-19",
        "absenceDuration": 2,
        "absenceApprovedResidency": true,
        "absenceApprovedArmy": true,
        "blockNumber": [
          "recWQEZ1WZ8lvXReP"
        ],
        "comments": "Imported from Excel: June 18 - 19"
      }
    },
    {
      "id": "recKDBRDpEub5HW49",
      "createdTime": "2025-08-26T22:43:32.000Z",
      "fields": {
        "absenceRequest": "TRUE - TRUE - PGY2-02 - 2026-02-04T00:00:00.000Z - 2026-02-08T00:00:00.000Z",
        "resident": [
          "recAtFCfEO8EjeJXh"
        ],
        "absenceId": "recKDBRDpEub5HW49",
        "postGraduateYear": [
          "rechgRuK16I8kTScb"
        ],
        "residentId": [
          "recAtFCfEO8EjeJXh"
        ],
        "absenceStart": "2026-02-04",
        "absenceEnd": "2026-02-08",
        "absenceDuration": 5,
        "absenceApprovedResidency": true,
        "absenceApprovedArmy": true,
        "blockNumber": [
          "recO8nXpj7mKdnOC2"
        ],
        "comments": "Imported from Excel: Feb 4 - 8 (Block 8)"
      }
    },
    {
      "id": "recKSYFMUi5uuICzV",
      "createdTime": "2025-08-18T18:06:13.000Z",
      "fields": {
        "absenceRequest": "TRUE - TRUE - PGY1-04 - 2026-03-14T00:00:00.000Z - 2026-03-20T00:00:00.000Z",
        "resident": [
          "recTstPguvGjy3jlb"
        ],
        "absenceId": "recKSYFMUi5uuICzV",
        "postGraduateYear": [
          "recBFlKB0nKMu8uqX"
        ],
        "residentId": [
          "recTstPguvGjy3jlb"
        ],
        "absenceStart": "2026-03-14",
        "absenceEnd": "2026-03-20",
        "absenceDuration": 7,
        "absenceApprovedResidency": true,
        "absenceApprovedArmy": true,
        "blockNumber": [
          "recHQVwPtmZwHBnGx"
        ],
        "comments": "Leave"
      }
    },
    {
      "id": "recMJVbmABObHIiDs",
      "createdTime": "2025-08-19T18:07:01.000Z",
      "fields": {
        "absenceRequest": "TRUE - TRUE - PGY1-03 - 2025-08-26T00:00:00.000Z - 2025-08-26T00:00:00.000Z",
        "resident": [
          "rec8sCH92dmDNq0Jy"
        ],
        "absenceId": "recMJVbmABObHIiDs",
        "postGraduateYear": [
          "recBFlKB0nKMu8uqX"
        ],
        "residentId": [
          "rec8sCH92dmDNq0Jy"
        ],
        "absenceStart": "2025-08-26",
        "absenceEnd": "2025-08-26",
        "absenceDuration": 1,
        "absenceApprovedResidency": true,
        "absenceApprovedArmy": true,
        "blockNumber": [
          "recba9vit0iwjDvyd"
        ],
        "comments": "Dental"
      }
    },
    {
      "id": "recN4YcDBSlQScN07",
      "createdTime": "2025-08-06T21:25:42.000Z",
      "fields": {
        "absenceRequest": "TRUE - TRUE - PGY2-04 - 2025-12-26T00:00:00.000Z - 2026-01-01T00:00:00.000Z",
        "resident": [
          "recSyteEOxDCJUCM1"
        ],
        "absenceId": "recN4YcDBSlQScN07",
        "postGraduateYear": [
          "rechgRuK16I8kTScb"
        ],
        "residentId": [
          "recSyteEOxDCJUCM1"
        ],
        "absenceStart": "2025-12-26",
        "absenceEnd": "2026-01-01",
        "absenceDuration": 7,
        "absenceApprovedResidency": true,
        "absenceApprovedArmy": true,
        "blockNumber": [
          "rec4QEhUx2W3VpbJg"
        ],
        "comments": "Leave"
      }
    },
    {
      "id": "recNo6uV2evq6OSeJ",
      "createdTime": "2025-08-26T22:48:38.000Z",
      "fields": {
        "absenceRequest": "TRUE - TRUE - PGY3-04 - 2025-10-03T00:00:00.000Z - 2025-10-03T00:00:00.000Z",
        "resident": [
          "recGZP0N9JXnYK2tq"
        ],
        "absenceId": "recNo6uV2evq6OSeJ",
        "postGraduateYear": [
          "recEWQHvAnrsTqGHO"
        ],
        "residentId": [
          "recGZP0N9JXnYK2tq"
        ],
        "absenceStart": "2025-10-03",
        "absenceEnd": "2025-10-03",
        "absenceDuration": 1,
        "absenceApprovedResidency": true,
        "absenceApprovedArmy": true,
        "blockNumber": [
          "recxSe9VbRMwt4DqQ"
        ],
        "comments": "Imported from Excel: Oct 3 (Block 4)"
      }
    },
    {
      "id": "recOiIfQ93mjoA4EJ",
      "createdTime": "2025-08-06T21:48:43.000Z",
      "fields": {
        "absenceRequest": "TRUE - TRUE - PGY3-04 - 2025-08-20T00:00:00.000Z - 2025-08-24T00:00:00.000Z",
        "resident": [
          "recGZP0N9JXnYK2tq"
        ],
        "absenceId": "recOiIfQ93mjoA4EJ",
        "postGraduateYear": [
          "recEWQHvAnrsTqGHO"
        ],
        "residentId": [
          "recGZP0N9JXnYK2tq"
        ],
        "absenceStart": "2025-08-20",
        "absenceEnd": "2025-08-24",
        "absenceDuration": 5,
        "absenceApprovedResidency": true,
        "absenceApprovedArmy": true,
        "blockNumber": [
          "recba9vit0iwjDvyd"
        ],
        "comments": "Leave"
      }
    },
    {
      "id": "recOpv6RNeSOIv4Iw",
      "createdTime": "2025-07-22T00:59:36.000Z",
      "fields": {
        "absenceRequest": "TRUE - TRUE - PGY2-02 - 2025-09-05T00:00:00.000Z - 2025-09-08T00:00:00.000Z",
        "resident": [
          "recAtFCfEO8EjeJXh"
        ],
        "absenceId": "recOpv6RNeSOIv4Iw",
        "postGraduateYear": [
          "rechgRuK16I8kTScb"
        ],
        "residentId": [
          "recAtFCfEO8EjeJXh"
        ],
        "absenceStart": "2025-09-05",
        "absenceEnd": "2025-09-08",
        "absenceDuration": 4,
        "absenceApprovedResidency": true,
        "absenceApprovedArmy": true,
        "blockNumber": [
          "recldLCwxBq8qUpNY"
        ],
        "comments": "Leave"
      }
    },
    {
      "id": "recP4CYRDfErgnFiT",
      "createdTime": "2025-08-26T22:41:30.000Z",
      "fields": {
        "absenceRequest": "TRUE - TRUE - PGY1-02 - 2025-12-15T00:00:00.000Z - 2025-12-21T00:00:00.000Z",
        "resident": [
          "rec6w0pOz3z54OaNH"
        ],
        "absenceId": "recP4CYRDfErgnFiT",
        "postGraduateYear": [
          "recBFlKB0nKMu8uqX"
        ],
        "residentId": [
          "rec6w0pOz3z54OaNH"
        ],
        "absenceStart": "2025-12-15",
        "absenceEnd": "2025-12-21",
        "absenceDuration": 7,
        "absenceApprovedResidency": true,
        "absenceApprovedArmy": true,
        "blockNumber": [
          "rec4QEhUx2W3VpbJg"
        ],
        "comments": "Imported from Excel: Dec 15 - 21 (Block 7)"
      }
    },
    {
      "id": "recQKw8sLXBvCjeVr",
      "createdTime": "2025-08-21T22:02:30.000Z",
      "fields": {
        "absenceRequest": "TRUE - TRUE - PGY2-03 - 2025-08-22T00:00:00.000Z - 2025-08-22T00:00:00.000Z",
        "resident": [
          "recEtslBYJpqYmdkd"
        ],
        "absenceId": "recQKw8sLXBvCjeVr",
        "postGraduateYear": [
          "rechgRuK16I8kTScb"
        ],
        "residentId": [
          "recEtslBYJpqYmdkd"
        ],
        "absenceStart": "2025-08-22",
        "absenceEnd": "2025-08-22",
        "absenceDuration": 1,
        "absenceApprovedResidency": true,
        "absenceApprovedArmy": true,
        "blockNumber": [
          "recba9vit0iwjDvyd"
        ],
        "comments": "12pm\u20135pm leave"
      }
    },
    {
      "id": "recSYRjt3Bm6aJNZv",
      "createdTime": "2025-08-26T22:45:24.000Z",
      "fields": {
        "absenceRequest": "TRUE - TRUE - PGY2-05 - 2026-05-03T00:00:00.000Z - 2026-05-06T00:00:00.000Z",
        "resident": [
          "recjkLHNGSlRaZA0R"
        ],
        "absenceId": "recSYRjt3Bm6aJNZv",
        "postGraduateYear": [
          "rechgRuK16I8kTScb"
        ],
        "residentId": [
          "recjkLHNGSlRaZA0R"
        ],
        "absenceStart": "2026-05-03",
        "absenceEnd": "2026-05-06",
        "absenceDuration": 4,
        "absenceApprovedResidency": true,
        "absenceApprovedArmy": true,
        "blockNumber": [
          "recukCPK15uxoCGtJ"
        ],
        "comments": "Imported from Excel: May 3 - 6"
      }
    },
    {
      "id": "recSnBdD6Ppwbw4v8",
      "createdTime": "2025-08-26T22:37:02.000Z",
      "fields": {
        "absenceRequest": "TRUE - TRUE - PGY1-01 - 2026-05-24T00:00:00.000Z - 2026-05-30T00:00:00.000Z",
        "resident": [
          "rec5jcPQWWX9phYCc"
        ],
        "absenceId": "recSnBdD6Ppwbw4v8",
        "postGraduateYear": [
          "recBFlKB0nKMu8uqX"
        ],
        "residentId": [
          "rec5jcPQWWX9phYCc"
        ],
        "absenceStart": "2026-05-24",
        "absenceEnd": "2026-05-30",
        "absenceDuration": 7,
        "absenceApprovedResidency": true,
        "absenceApprovedArmy": true,
        "blockNumber": [
          "rectoByFjGEhCHnP0"
        ],
        "comments": "Imported from Excel: May 24 - 30 (Block 12)"
      }
    },
    {
      "id": "recTiyIgfMMfT4PHm",
      "createdTime": "2025-08-06T22:08:05.000Z",
      "fields": {
        "absenceRequest": "TRUE - TRUE - PGY3-01 - 2025-10-05T00:00:00.000Z - 2025-10-11T00:00:00.000Z",
        "resident": [
          "rec5HLr3R4qE79jK0"
        ],
        "absenceId": "recTiyIgfMMfT4PHm",
        "postGraduateYear": [
          "recEWQHvAnrsTqGHO"
        ],
        "residentId": [
          "rec5HLr3R4qE79jK0"
        ],
        "absenceStart": "2025-10-05",
        "absenceEnd": "2025-10-11",
        "absenceDuration": 7,
        "absenceApprovedResidency": true,
        "absenceApprovedArmy": true,
        "blockNumber": [
          "recxSe9VbRMwt4DqQ"
        ],
        "comments": "Leave"
      }
    },
    {
      "id": "recUlCrilNnQ9Uitx",
      "createdTime": "2025-08-26T22:46:26.000Z",
      "fields": {
        "absenceRequest": "TRUE - TRUE - PGY2-01 - 2026-02-09T00:00:00.000Z - 2026-02-11T00:00:00.000Z",
        "resident": [
          "rec3TityYwwXKG80J"
        ],
        "absenceId": "recUlCrilNnQ9Uitx",
        "postGraduateYear": [
          "rechgRuK16I8kTScb"
        ],
        "residentId": [
          "rec3TityYwwXKG80J"
        ],
        "absenceStart": "2026-02-09",
        "absenceEnd": "2026-02-11",
        "absenceDuration": 3,
        "absenceApprovedResidency": true,
        "absenceApprovedArmy": true,
        "blockNumber": [
          "recO8nXpj7mKdnOC2"
        ],
        "comments": "Imported from Excel: Feb 9 - 11 (Block 8)"
      }
    },
    {
      "id": "recV9dvHQm1hmw87m",
      "createdTime": "2025-08-06T22:02:29.000Z",
      "fields": {
        "absenceRequest": "TRUE - TRUE - PGY1-05 - 2025-08-18T00:00:00.000Z - 2025-08-24T00:00:00.000Z",
        "resident": [
          "recdJZeXQjXmXhP4Q"
        ],
        "absenceId": "recV9dvHQm1hmw87m",
        "postGraduateYear": [
          "recBFlKB0nKMu8uqX"
        ],
        "residentId": [
          "recdJZeXQjXmXhP4Q"
        ],
        "absenceStart": "2025-08-18",
        "absenceEnd": "2025-08-24",
        "absenceDuration": 7,
        "absenceApprovedResidency": true,
        "absenceApprovedArmy": true,
        "blockNumber": [
          "recba9vit0iwjDvyd"
        ],
        "comments": "Leave"
      }
    },
    {
      "id": "recVFL4IpKuOvI7qX",
      "createdTime": "2025-08-26T22:48:31.000Z",
      "fields": {
        "absenceRequest": "TRUE - TRUE - PGY3-04 - 2025-12-21T00:00:00.000Z - 2026-01-04T00:00:00.000Z",
        "resident": [
          "recGZP0N9JXnYK2tq"
        ],
        "absenceId": "recVFL4IpKuOvI7qX",
        "postGraduateYear": [
          "recEWQHvAnrsTqGHO"
        ],
        "residentId": [
          "recGZP0N9JXnYK2tq"
        ],
        "absenceStart": "2025-12-21",
        "absenceEnd": "2026-01-04",
        "absenceDuration": 15,
        "absenceApprovedResidency": true,
        "absenceApprovedArmy": true,
        "blockNumber": [
          "rec4QEhUx2W3VpbJg"
        ],
        "comments": "Imported from Excel: Dec 21 - Jan 4 (Block 7)"
      }
    },
    {
      "id": "recVONKUMf1QEHuLM",
      "createdTime": "2025-07-22T00:59:27.000Z",
      "fields": {
        "absenceRequest": "TRUE - TRUE - PGY2-04 - 2025-09-18T00:00:00.000Z - 2025-09-25T00:00:00.000Z",
        "resident": [
          "recSyteEOxDCJUCM1"
        ],
        "absenceId": "recVONKUMf1QEHuLM",
        "postGraduateYear": [
          "rechgRuK16I8kTScb"
        ],
        "residentId": [
          "recSyteEOxDCJUCM1"
        ],
        "absenceStart": "2025-09-18",
        "absenceEnd": "2025-09-25",
        "absenceDuration": 8,
        "absenceApprovedResidency": true,
        "absenceApprovedArmy": true,
        "blockNumber": [
          "recldLCwxBq8qUpNY",
          "recxSe9VbRMwt4DqQ"
        ],
        "comments": "Leave"
      }
    },
    {
      "id": "recWmIlsZ88fhOjIZ",
      "createdTime": "2025-08-26T22:45:47.000Z",
      "fields": {
        "absenceRequest": "TRUE - TRUE - PGY2-06 - 2025-10-31T00:00:00.000Z - 2025-10-31T00:00:00.000Z",
        "resident": [
          "recyynCFupNGxL9NK"
        ],
        "absenceId": "recWmIlsZ88fhOjIZ",
        "postGraduateYear": [
          "rechgRuK16I8kTScb"
        ],
        "residentId": [
          "recyynCFupNGxL9NK"
        ],
        "absenceStart": "2025-10-31",
        "absenceEnd": "2025-10-31",
        "absenceDuration": 1,
        "absenceApprovedResidency": true,
        "absenceApprovedArmy": true,
        "blockNumber": [
          "reciDYU7hTsmjgAaT"
        ],
        "comments": "Imported from Excel: Oct 31 (Block 5)"
      }
    },
    {
      "id": "recXhpKm9rKfRvhNV",
      "createdTime": "2025-08-26T22:41:38.000Z",
      "fields": {
        "absenceRequest": "TRUE - TRUE - PGY1-02 - 2026-02-09T00:00:00.000Z - 2026-02-15T00:00:00.000Z",
        "resident": [
          "rec6w0pOz3z54OaNH"
        ],
        "absenceId": "recXhpKm9rKfRvhNV",
        "postGraduateYear": [
          "recBFlKB0nKMu8uqX"
        ],
        "residentId": [
          "rec6w0pOz3z54OaNH"
        ],
        "absenceStart": "2026-02-09",
        "absenceEnd": "2026-02-15",
        "absenceDuration": 7,
        "absenceApprovedResidency": true,
        "absenceApprovedArmy": true,
        "blockNumber": [
          "rec9KG7LgejhaAdDP"
        ],
        "comments": "Imported from Excel: Feb 9 - 15 (Block 9)"
      }
    },
    {
      "id": "recXyvRSvBcQ381oJ",
      "createdTime": "2025-08-06T21:55:34.000Z",
      "fields": {
        "absenceRequest": "TRUE - TRUE - PGY1-04 - 2025-11-26T00:00:00.000Z - 2025-11-28T00:00:00.000Z",
        "resident": [
          "recTstPguvGjy3jlb"
        ],
        "absenceId": "recXyvRSvBcQ381oJ",
        "postGraduateYear": [
          "recBFlKB0nKMu8uqX"
        ],
        "residentId": [
          "recTstPguvGjy3jlb"
        ],
        "absenceStart": "2025-11-26",
        "absenceEnd": "2025-11-28",
        "absenceDuration": 3,
        "absenceApprovedResidency": true,
        "absenceApprovedArmy": true,
        "blockNumber": [
          "recheHoNFIphdOOkc"
        ],
        "comments": "Leave"
      }
    },
    {
      "id": "recZR76dVJcnnHei8",
      "createdTime": "2025-07-22T00:59:00.000Z",
      "fields": {
        "absenceRequest": "TRUE - TRUE - PGY1-06 - 2025-09-01T00:00:00.000Z - 2025-09-07T00:00:00.000Z",
        "resident": [
          "recsi4ZOjSvEoVT7m"
        ],
        "absenceId": "recZR76dVJcnnHei8",
        "postGraduateYear": [
          "recBFlKB0nKMu8uqX"
        ],
        "residentId": [
          "recsi4ZOjSvEoVT7m"
        ],
        "absenceStart": "2025-09-01",
        "absenceEnd": "2025-09-07",
        "absenceDuration": 7,
        "absenceApprovedResidency": true,
        "absenceApprovedArmy": true,
        "blockNumber": [
          "recldLCwxBq8qUpNY"
        ],
        "comments": "Leave"
      }
    },
    {
      "id": "recZTPo13eWlsXXdL",
      "createdTime": "2025-08-06T21:56:35.000Z",
      "fields": {
        "absenceRequest": "TRUE - TRUE - PGY1-04 - 2025-12-22T00:00:00.000Z - 2025-12-28T00:00:00.000Z",
        "resident": [
          "recTstPguvGjy3jlb"
        ],
        "absenceId": "recZTPo13eWlsXXdL",
        "postGraduateYear": [
          "recBFlKB0nKMu8uqX"
        ],
        "residentId": [
          "recTstPguvGjy3jlb"
        ],
        "absenceStart": "2025-12-22",
        "absenceEnd": "2025-12-28",
        "absenceDuration": 7,
        "absenceApprovedResidency": true,
        "absenceApprovedArmy": true,
        "blockNumber": [
          "rec4QEhUx2W3VpbJg"
        ],
        "comments": "Leave"
      }
    },
    {
      "id": "recZifURlhG6xwCCr",
      "createdTime": "2025-08-11T22:19:48.000Z",
      "fields": {
        "absenceRequest": "TRUE - TRUE - PGY1-01 - 2025-12-16T00:00:00.000Z - 2025-12-16T00:00:00.000Z",
        "resident": [
          "rec5jcPQWWX9phYCc"
        ],
        "absenceId": "recZifURlhG6xwCCr",
        "postGraduateYear": [
          "recBFlKB0nKMu8uqX"
        ],
        "residentId": [
          "rec5jcPQWWX9phYCc"
        ],
        "absenceStart": "2025-12-16",
        "absenceEnd": "2025-12-16",
        "absenceDuration": 1,
        "absenceApprovedResidency": true,
        "absenceApprovedArmy": true,
        "blockNumber": [
          "recheHoNFIphdOOkc"
        ],
        "comments": "Leave"
      }
    },
    {
      "id": "recbAeL2P8xXjy4MX",
      "createdTime": "2025-08-26T22:42:14.000Z",
      "fields": {
        "absenceRequest": "TRUE - TRUE - PGY1-03 - 2026-02-12T00:00:00.000Z - 2026-02-15T00:00:00.000Z",
        "resident": [
          "rec8sCH92dmDNq0Jy"
        ],
        "absenceId": "recbAeL2P8xXjy4MX",
        "postGraduateYear": [
          "recBFlKB0nKMu8uqX"
        ],
        "residentId": [
          "rec8sCH92dmDNq0Jy"
        ],
        "absenceStart": "2026-02-12",
        "absenceEnd": "2026-02-15",
        "absenceDuration": 4,
        "absenceApprovedResidency": true,
        "absenceApprovedArmy": true,
        "blockNumber": [
          "rec9KG7LgejhaAdDP"
        ],
        "comments": "Imported from Excel: Feb 12 - 15 (Block 9)"
      }
    },
    {
      "id": "recbSraZyhTvffCgx",
      "createdTime": "2025-08-06T22:01:59.000Z",
      "fields": {
        "absenceRequest": "TRUE - TRUE - PGY1-03 - 2025-11-24T00:00:00.000Z - 2025-11-30T00:00:00.000Z",
        "resident": [
          "rec8sCH92dmDNq0Jy"
        ],
        "absenceId": "recbSraZyhTvffCgx",
        "postGraduateYear": [
          "recBFlKB0nKMu8uqX"
        ],
        "residentId": [
          "rec8sCH92dmDNq0Jy"
        ],
        "absenceStart": "2025-11-24",
        "absenceEnd": "2025-11-30",
        "absenceDuration": 7,
        "absenceApprovedResidency": true,
        "absenceApprovedArmy": true,
        "blockNumber": [
          "recheHoNFIphdOOkc"
        ],
        "comments": "Leave"
      }
    },
    {
      "id": "reccAv2OEauCgW8v3",
      "createdTime": "2025-07-16T23:42:09.000Z",
      "fields": {
        "absenceRequest": "TRUE - TRUE - PGY2-03 - 2025-08-20T00:00:00.000Z - 2025-08-26T00:00:00.000Z",
        "resident": [
          "recEtslBYJpqYmdkd"
        ],
        "absenceId": "reccAv2OEauCgW8v3",
        "postGraduateYear": [
          "rechgRuK16I8kTScb"
        ],
        "residentId": [
          "recEtslBYJpqYmdkd"
        ],
        "absenceStart": "2025-08-20",
        "absenceEnd": "2025-08-26",
        "absenceDuration": 7,
        "absenceApprovedResidency": true,
        "absenceApprovedArmy": true,
        "blockNumber": [
          "recba9vit0iwjDvyd"
        ],
        "comments": "Leave"
      }
    },
    {
      "id": "recdKJjfXaM2E9R07",
      "createdTime": "2025-07-22T00:59:43.000Z",
      "fields": {
        "absenceRequest": "TRUE - TRUE - PGY3-03 - 2025-09-03T00:00:00.000Z - 2025-09-09T00:00:00.000Z",
        "resident": [
          "rec8tD8mJTRq51ewo"
        ],
        "absenceId": "recdKJjfXaM2E9R07",
        "postGraduateYear": [
          "recEWQHvAnrsTqGHO"
        ],
        "residentId": [
          "rec8tD8mJTRq51ewo"
        ],
        "absenceStart": "2025-09-03",
        "absenceEnd": "2025-09-09",
        "absenceDuration": 7,
        "absenceApprovedResidency": true,
        "absenceApprovedArmy": true,
        "blockNumber": [
          "recldLCwxBq8qUpNY"
        ],
        "comments": "Leave"
      }
    },
    {
      "id": "recdNHFdCtFZFYJf4",
      "createdTime": "2025-07-22T00:59:19.000Z",
      "fields": {
        "absenceRequest": "TRUE - TRUE - PGY2-03 - 2025-09-20T00:00:00.000Z - 2025-09-23T00:00:00.000Z",
        "resident": [
          "recEtslBYJpqYmdkd"
        ],
        "absenceId": "recdNHFdCtFZFYJf4",
        "postGraduateYear": [
          "rechgRuK16I8kTScb"
        ],
        "residentId": [
          "recEtslBYJpqYmdkd"
        ],
        "absenceStart": "2025-09-20",
        "absenceEnd": "2025-09-23",
        "absenceDuration": 4,
        "absenceApprovedResidency": true,
        "absenceApprovedArmy": true,
        "blockNumber": [
          "recldLCwxBq8qUpNY"
        ],
        "comments": "Leave"
      }
    },
    {
      "id": "recdVIlkXa2Q5KtRy",
      "createdTime": "2025-08-06T21:57:26.000Z",
      "fields": {
        "absenceRequest": "TRUE - TRUE - PGY1-01 - 2025-10-05T00:00:00.000Z - 2025-10-11T00:00:00.000Z",
        "resident": [
          "rec5jcPQWWX9phYCc"
        ],
        "absenceId": "recdVIlkXa2Q5KtRy",
        "postGraduateYear": [
          "recBFlKB0nKMu8uqX"
        ],
        "residentId": [
          "rec5jcPQWWX9phYCc"
        ],
        "absenceStart": "2025-10-05",
        "absenceEnd": "2025-10-11",
        "absenceDuration": 7,
        "absenceApprovedResidency": true,
        "absenceApprovedArmy": true,
        "blockNumber": [
          "recxSe9VbRMwt4DqQ"
        ],
        "comments": "Leave"
      }
    },
    {
      "id": "recdcDN7azvdwiABJ",
      "createdTime": "2025-08-26T22:45:55.000Z",
      "fields": {
        "absenceRequest": "TRUE - TRUE - PGY2-06 - 2025-12-22T00:00:00.000Z - 2025-12-26T00:00:00.000Z",
        "resident": [
          "recyynCFupNGxL9NK"
        ],
        "absenceId": "recdcDN7azvdwiABJ",
        "postGraduateYear": [
          "rechgRuK16I8kTScb"
        ],
        "residentId": [
          "recyynCFupNGxL9NK"
        ],
        "absenceStart": "2025-12-22",
        "absenceEnd": "2025-12-26",
        "absenceDuration": 5,
        "absenceApprovedResidency": true,
        "absenceApprovedArmy": true,
        "blockNumber": [
          "rec4QEhUx2W3VpbJg"
        ],
        "comments": "Imported from Excel: Dec 22- 26 (Block 7)"
      }
    },
    {
      "id": "recdkMWObmLHnTtzn",
      "createdTime": "2025-08-26T22:46:16.000Z",
      "fields": {
        "absenceRequest": "TRUE - TRUE - PGY2-01 - 2025-12-23T00:00:00.000Z - 2025-12-29T00:00:00.000Z",
        "resident": [
          "rec3TityYwwXKG80J"
        ],
        "absenceId": "recdkMWObmLHnTtzn",
        "postGraduateYear": [
          "rechgRuK16I8kTScb"
        ],
        "residentId": [
          "rec3TityYwwXKG80J"
        ],
        "absenceStart": "2025-12-23",
        "absenceEnd": "2025-12-29",
        "absenceDuration": 7,
        "absenceApprovedResidency": true,
        "absenceApprovedArmy": true,
        "blockNumber": [
          "rec4QEhUx2W3VpbJg"
        ],
        "comments": "Imported from Excel: Dec 23 - 29 (Block 7)"
      }
    },
    {
      "id": "rece2kpv50RFYry44",
      "createdTime": "2025-08-26T22:43:08.000Z",
      "fields": {
        "absenceRequest": "TRUE - TRUE - PGY2-02 - 2025-08-18T00:00:00.000Z - 2025-08-24T00:00:00.000Z",
        "resident": [
          "recAtFCfEO8EjeJXh"
        ],
        "absenceId": "rece2kpv50RFYry44",
        "postGraduateYear": [
          "rechgRuK16I8kTScb"
        ],
        "residentId": [
          "recAtFCfEO8EjeJXh"
        ],
        "absenceStart": "2025-08-18",
        "absenceEnd": "2025-08-24",
        "absenceDuration": 7,
        "absenceApprovedResidency": true,
        "absenceApprovedArmy": true,
        "blockNumber": [
          "recba9vit0iwjDvyd"
        ],
        "comments": "Imported from Excel: Aug 18 - 24 (Block 2)"
      }
    },
    {
      "id": "receHpAHOBggfbCZZ",
      "createdTime": "2025-08-26T22:47:40.000Z",
      "fields": {
        "absenceRequest": "TRUE - TRUE - PGY3-03 - 2025-08-17T00:00:00.000Z - 2025-08-23T00:00:00.000Z",
        "resident": [
          "rec8tD8mJTRq51ewo"
        ],
        "absenceId": "receHpAHOBggfbCZZ",
        "postGraduateYear": [
          "recEWQHvAnrsTqGHO"
        ],
        "residentId": [
          "rec8tD8mJTRq51ewo"
        ],
        "absenceStart": "2025-08-17",
        "absenceEnd": "2025-08-23",
        "absenceDuration": 7,
        "absenceApprovedResidency": true,
        "absenceApprovedArmy": true,
        "blockNumber": [
          "recba9vit0iwjDvyd"
        ],
        "comments": "Imported from Excel: Aug 17 - 23 (Block 2)"
      }
    },
    {
      "id": "receXnvRbjNJ3qOHu",
      "createdTime": "2025-07-22T00:59:10.000Z",
      "fields": {
        "absenceRequest": "TRUE - TRUE - PGY1-04 - 2025-09-12T00:00:00.000Z - 2025-09-18T00:00:00.000Z",
        "resident": [
          "recTstPguvGjy3jlb"
        ],
        "absenceId": "receXnvRbjNJ3qOHu",
        "postGraduateYear": [
          "recBFlKB0nKMu8uqX"
        ],
        "residentId": [
          "recTstPguvGjy3jlb"
        ],
        "absenceStart": "2025-09-12",
        "absenceEnd": "2025-09-18",
        "absenceDuration": 7,
        "absenceApprovedResidency": true,
        "absenceApprovedArmy": true,
        "blockNumber": [
          "recldLCwxBq8qUpNY"
        ],
        "comments": "Leave"
      }
    },
    {
      "id": "receYyxHN8EQOdMIo",
      "createdTime": "2025-06-28T19:51:47.000Z",
      "fields": {
        "absenceRequest": "TRUE - TRUE - PGY2-03 - 2026-02-18T00:00:00.000Z - 2026-02-27T00:00:00.000Z",
        "resident": [
          "recEtslBYJpqYmdkd"
        ],
        "absenceId": "receYyxHN8EQOdMIo",
        "postGraduateYear": [
          "rechgRuK16I8kTScb"
        ],
        "residentId": [
          "recEtslBYJpqYmdkd"
        ],
        "absenceStart": "2026-02-18",
        "absenceEnd": "2026-02-27",
        "absenceDuration": 10,
        "absenceApprovedResidency": true,
        "absenceApprovedArmy": true,
        "blockNumber": [
          "rec9KG7LgejhaAdDP"
        ],
        "comments": "C4"
      }
    },
    {
      "id": "recf2EdyAvcJ1IryZ",
      "createdTime": "2025-08-06T21:58:10.000Z",
      "fields": {
        "absenceRequest": "TRUE - TRUE - PGY1-01 - 2025-12-07T00:00:00.000Z - 2025-12-13T00:00:00.000Z",
        "resident": [
          "rec5jcPQWWX9phYCc"
        ],
        "absenceId": "recf2EdyAvcJ1IryZ",
        "postGraduateYear": [
          "recBFlKB0nKMu8uqX"
        ],
        "residentId": [
          "rec5jcPQWWX9phYCc"
        ],
        "absenceStart": "2025-12-07",
        "absenceEnd": "2025-12-13",
        "absenceDuration": 7,
        "absenceApprovedResidency": true,
        "absenceApprovedArmy": true,
        "blockNumber": [
          "recheHoNFIphdOOkc"
        ],
        "comments": "Leave"
      }
    },
    {
      "id": "recfQIUfIr2C7kJWK",
      "createdTime": "2025-08-26T22:42:05.000Z",
      "fields": {
        "absenceRequest": "TRUE - TRUE - PGY1-03 - 2025-11-24T00:00:00.000Z - 2025-11-30T00:00:00.000Z",
        "resident": [
          "rec8sCH92dmDNq0Jy"
        ],
        "absenceId": "recfQIUfIr2C7kJWK",
        "postGraduateYear": [
          "recBFlKB0nKMu8uqX"
        ],
        "residentId": [
          "rec8sCH92dmDNq0Jy"
        ],
        "absenceStart": "2025-11-24",
        "absenceEnd": "2025-11-30",
        "absenceDuration": 7,
        "absenceApprovedResidency": true,
        "absenceApprovedArmy": true,
        "blockNumber": [
          "recheHoNFIphdOOkc"
        ],
        "comments": "Imported from Excel: Nov 24 - 30 (Block 6)"
      }
    },
    {
      "id": "recfbWBiM6x2CBvx1",
      "createdTime": "2025-08-26T22:43:16.000Z",
      "fields": {
        "absenceRequest": "TRUE - TRUE - PGY2-02 - 2025-10-18T00:00:00.000Z - 2025-10-21T00:00:00.000Z",
        "resident": [
          "recAtFCfEO8EjeJXh"
        ],
        "absenceId": "recfbWBiM6x2CBvx1",
        "postGraduateYear": [
          "rechgRuK16I8kTScb"
        ],
        "residentId": [
          "recAtFCfEO8EjeJXh"
        ],
        "absenceStart": "2025-10-18",
        "absenceEnd": "2025-10-21",
        "absenceDuration": 4,
        "absenceApprovedResidency": true,
        "absenceApprovedArmy": true,
        "blockNumber": [
          "recxSe9VbRMwt4DqQ"
        ],
        "comments": "Imported from Excel: Oct 18 - 21 (Block 4)"
      }
    },
    {
      "id": "recfze7imLiSPiJs5",
      "createdTime": "2025-05-29T02:07:51.000Z",
      "fields": {
        "absenceRequest": "TRUE - TRUE - PGY2-01 - 2025-07-05T00:00:00.000Z - 2025-07-11T00:00:00.000Z",
        "resident": [
          "rec3TityYwwXKG80J"
        ],
        "absenceId": "recfze7imLiSPiJs5",
        "postGraduateYear": [
          "rechgRuK16I8kTScb"
        ],
        "residentId": [
          "rec3TityYwwXKG80J"
        ],
        "absenceStart": "2025-07-05",
        "absenceEnd": "2025-07-11",
        "absenceDuration": 7,
        "absenceApprovedResidency": true,
        "absenceApprovedArmy": true,
        "blockNumber": [
          "recyCXLCOdygmwkaB"
        ],
        "comments": "Leave"
      }
    },
    {
      "id": "recgg1LxzdddHuLhX",
      "createdTime": "2025-05-29T02:16:16.000Z",
      "fields": {
        "absenceRequest": "TRUE - TRUE - PGY3-05 - 2025-07-24T00:00:00.000Z - 2025-08-05T00:00:00.000Z",
        "resident": [
          "recfCEd4ydvmWPMbq"
        ],
        "absenceId": "recgg1LxzdddHuLhX",
        "postGraduateYear": [
          "recEWQHvAnrsTqGHO"
        ],
        "residentId": [
          "recfCEd4ydvmWPMbq"
        ],
        "absenceStart": "2025-07-24",
        "absenceEnd": "2025-08-05",
        "absenceDuration": 13,
        "absenceApprovedResidency": true,
        "absenceApprovedArmy": true,
        "blockNumber": [
          "recyCXLCOdygmwkaB",
          "recba9vit0iwjDvyd"
        ],
        "comments": "Leave"
      }
    },
    {
      "id": "reci2y6zyWkDTWNJo",
      "createdTime": "2025-06-28T19:53:48.000Z",
      "fields": {
        "absenceRequest": "TRUE - TRUE - PGY2-04 - 2026-03-25T00:00:00.000Z - 2026-04-03T00:00:00.000Z",
        "resident": [
          "recSyteEOxDCJUCM1"
        ],
        "absenceId": "reci2y6zyWkDTWNJo",
        "postGraduateYear": [
          "rechgRuK16I8kTScb"
        ],
        "residentId": [
          "recSyteEOxDCJUCM1"
        ],
        "absenceStart": "2026-03-25",
        "absenceEnd": "2026-04-03",
        "absenceDuration": 10,
        "absenceApprovedResidency": true,
        "absenceApprovedArmy": true,
        "blockNumber": [
          "recHQVwPtmZwHBnGx"
        ],
        "comments": "C4"
      }
    },
    {
      "id": "reci8cYBCK8tfLQYG",
      "createdTime": "2025-08-06T22:10:02.000Z",
      "fields": {
        "absenceRequest": "TRUE - TRUE - PGY3-01 - 2025-12-01T00:00:00.000Z - 2025-12-07T00:00:00.000Z",
        "resident": [
          "rec5HLr3R4qE79jK0"
        ],
        "absenceId": "reci8cYBCK8tfLQYG",
        "postGraduateYear": [
          "recEWQHvAnrsTqGHO"
        ],
        "residentId": [
          "rec5HLr3R4qE79jK0"
        ],
        "absenceStart": "2025-12-01",
        "absenceEnd": "2025-12-07",
        "absenceDuration": 7,
        "absenceApprovedResidency": true,
        "absenceApprovedArmy": true,
        "blockNumber": [
          "recheHoNFIphdOOkc"
        ],
        "comments": "Leave"
      }
    },
    {
      "id": "reckYO9kp15Hfs6uP",
      "createdTime": "2025-08-26T22:45:08.000Z",
      "fields": {
        "absenceRequest": "TRUE - TRUE - PGY2-05 - 2025-11-26T00:00:00.000Z - 2025-11-30T00:00:00.000Z",
        "resident": [
          "recjkLHNGSlRaZA0R"
        ],
        "absenceId": "reckYO9kp15Hfs6uP",
        "postGraduateYear": [
          "rechgRuK16I8kTScb"
        ],
        "residentId": [
          "recjkLHNGSlRaZA0R"
        ],
        "absenceStart": "2025-11-26",
        "absenceEnd": "2025-11-30",
        "absenceDuration": 5,
        "absenceApprovedResidency": true,
        "absenceApprovedArmy": true,
        "blockNumber": [
          "recheHoNFIphdOOkc"
        ],
        "comments": "Imported from Excel: Nov 26 - 30 (Block 6)"
      }
    },
    {
      "id": "reckmXV3KWqmaW5do",
      "createdTime": "2025-08-26T22:48:12.000Z",
      "fields": {
        "absenceRequest": "TRUE - TRUE - PGY3-03 - 2026-06-14T00:00:00.000Z - 2026-06-20T00:00:00.000Z",
        "resident": [
          "rec8tD8mJTRq51ewo"
        ],
        "absenceId": "reckmXV3KWqmaW5do",
        "postGraduateYear": [
          "recEWQHvAnrsTqGHO"
        ],
        "residentId": [
          "rec8tD8mJTRq51ewo"
        ],
        "absenceStart": "2026-06-14",
        "absenceEnd": "2026-06-20",
        "absenceDuration": 7,
        "absenceApprovedResidency": true,
        "absenceApprovedArmy": true,
        "blockNumber": [
          "recWQEZ1WZ8lvXReP"
        ],
        "comments": "Imported from Excel: June 14 - 20 (Block 13)"
      }
    },
    {
      "id": "reclD9kDDkflcvQFe",
      "createdTime": "2025-05-29T02:09:19.000Z",
      "fields": {
        "absenceRequest": "TRUE - TRUE - PGY3-02 - 2025-07-07T00:00:00.000Z - 2025-07-09T00:00:00.000Z",
        "resident": [
          "rec72mJXy7UnA5R1n"
        ],
        "absenceId": "reclD9kDDkflcvQFe",
        "postGraduateYear": [
          "recEWQHvAnrsTqGHO"
        ],
        "residentId": [
          "rec72mJXy7UnA5R1n"
        ],
        "absenceStart": "2025-07-07",
        "absenceEnd": "2025-07-09",
        "absenceDuration": 3,
        "absenceApprovedResidency": true,
        "absenceApprovedArmy": true,
        "blockNumber": [
          "recyCXLCOdygmwkaB"
        ],
        "comments": "Leave"
      }
    },
    {
      "id": "recllP9iK2Pxnqkqs",
      "createdTime": "2025-08-26T22:47:31.000Z",
      "fields": {
        "absenceRequest": "TRUE - TRUE - PGY3-02 - 2026-06-01T00:00:00.000Z - 2026-06-07T00:00:00.000Z",
        "resident": [
          "rec72mJXy7UnA5R1n"
        ],
        "absenceId": "recllP9iK2Pxnqkqs",
        "postGraduateYear": [
          "recEWQHvAnrsTqGHO"
        ],
        "residentId": [
          "rec72mJXy7UnA5R1n"
        ],
        "absenceStart": "2026-06-01",
        "absenceEnd": "2026-06-07",
        "absenceDuration": 7,
        "absenceApprovedResidency": true,
        "absenceApprovedArmy": true,
        "blockNumber": [
          "recWQEZ1WZ8lvXReP"
        ],
        "comments": "Imported from Excel: June 1-7 (Block 13)"
      }
    },
    {
      "id": "reclsF1pPvHCztsxG",
      "createdTime": "2025-08-21T22:02:50.000Z",
      "fields": {
        "absenceRequest": "TRUE - TRUE - PGY2-03 - 2025-08-26T00:00:00.000Z - 2025-08-26T00:00:00.000Z",
        "resident": [
          "recEtslBYJpqYmdkd"
        ],
        "absenceId": "reclsF1pPvHCztsxG",
        "postGraduateYear": [
          "rechgRuK16I8kTScb"
        ],
        "residentId": [
          "recEtslBYJpqYmdkd"
        ],
        "absenceStart": "2025-08-26",
        "absenceEnd": "2025-08-26",
        "absenceDuration": 1,
        "absenceApprovedResidency": true,
        "absenceApprovedArmy": true,
        "blockNumber": [
          "recba9vit0iwjDvyd"
        ],
        "comments": "7am\u201312pm & 12pm\u20135pm leave (full day)"
      }
    },
    {
      "id": "recmAb934QPqWheoD",
      "createdTime": "2025-08-26T22:45:17.000Z",
      "fields": {
        "absenceRequest": "TRUE - TRUE - PGY2-05 - 2026-02-22T00:00:00.000Z - 2026-02-25T00:00:00.000Z",
        "resident": [
          "recjkLHNGSlRaZA0R"
        ],
        "absenceId": "recmAb934QPqWheoD",
        "postGraduateYear": [
          "rechgRuK16I8kTScb"
        ],
        "residentId": [
          "recjkLHNGSlRaZA0R"
        ],
        "absenceStart": "2026-02-22",
        "absenceEnd": "2026-02-25",
        "absenceDuration": 4,
        "absenceApprovedResidency": true,
        "absenceApprovedArmy": true,
        "blockNumber": [
          "rec9KG7LgejhaAdDP"
        ],
        "comments": "Imported from Excel: Feb 22 - 25 (Block 9)"
      }
    },
    {
      "id": "recmeE0CE5CNaidyT",
      "createdTime": "2025-08-26T22:45:00.000Z",
      "fields": {
        "absenceRequest": "TRUE - TRUE - PGY2-05 - 2025-09-14T00:00:00.000Z - 2025-09-18T00:00:00.000Z",
        "resident": [
          "recjkLHNGSlRaZA0R"
        ],
        "absenceId": "recmeE0CE5CNaidyT",
        "postGraduateYear": [
          "rechgRuK16I8kTScb"
        ],
        "residentId": [
          "recjkLHNGSlRaZA0R"
        ],
        "absenceStart": "2025-09-14",
        "absenceEnd": "2025-09-18",
        "absenceDuration": 5,
        "absenceApprovedResidency": true,
        "absenceApprovedArmy": true,
        "blockNumber": [
          "recldLCwxBq8qUpNY"
        ],
        "comments": "Imported from Excel: Sep 14 - 18 (Block 3)"
      }
    },
    {
      "id": "recniik1nv9Cwmvfz",
      "createdTime": "2025-08-26T22:36:54.000Z",
      "fields": {
        "absenceRequest": "TRUE - TRUE - PGY1-01 - 2026-02-08T00:00:00.000Z - 2026-02-11T00:00:00.000Z",
        "resident": [
          "rec5jcPQWWX9phYCc"
        ],
        "absenceId": "recniik1nv9Cwmvfz",
        "postGraduateYear": [
          "recBFlKB0nKMu8uqX"
        ],
        "residentId": [
          "rec5jcPQWWX9phYCc"
        ],
        "absenceStart": "2026-02-08",
        "absenceEnd": "2026-02-11",
        "absenceDuration": 4,
        "absenceApprovedResidency": true,
        "absenceApprovedArmy": true,
        "blockNumber": [
          "recO8nXpj7mKdnOC2"
        ],
        "comments": "Imported from Excel: Feb 8 - 11 (Block 8)"
      }
    },
    {
      "id": "reco9oGnHSDthx8q9",
      "createdTime": "2025-08-22T20:37:25.000Z",
      "fields": {
        "absenceRequest": "TRUE - TRUE - PGY1-05 - 2025-12-07T00:00:00.000Z - 2025-12-13T00:00:00.000Z",
        "resident": [
          "recdJZeXQjXmXhP4Q"
        ],
        "absenceId": "reco9oGnHSDthx8q9",
        "postGraduateYear": [
          "recBFlKB0nKMu8uqX"
        ],
        "residentId": [
          "recdJZeXQjXmXhP4Q"
        ],
        "absenceStart": "2025-12-07",
        "absenceEnd": "2025-12-13",
        "absenceDuration": 7,
        "absenceApprovedResidency": true,
        "absenceApprovedArmy": true,
        "blockNumber": [
          "recheHoNFIphdOOkc"
        ],
        "comments": "COMLEX Level 3 on 12/08; leave approved per Chiefs reminder."
      }
    },
    {
      "id": "recoGArTIxa6YBhKV",
      "createdTime": "2025-08-26T22:42:32.000Z",
      "fields": {
        "absenceRequest": "TRUE - TRUE - PGY1-05 - 2025-11-26T00:00:00.000Z - 2025-11-30T00:00:00.000Z",
        "resident": [
          "recdJZeXQjXmXhP4Q"
        ],
        "absenceId": "recoGArTIxa6YBhKV",
        "postGraduateYear": [
          "recBFlKB0nKMu8uqX"
        ],
        "residentId": [
          "recdJZeXQjXmXhP4Q"
        ],
        "absenceStart": "2025-11-26",
        "absenceEnd": "2025-11-30",
        "absenceDuration": 5,
        "absenceApprovedResidency": true,
        "absenceApprovedArmy": true,
        "blockNumber": [
          "recheHoNFIphdOOkc"
        ],
        "comments": "Imported from Excel: Nov 26 - 30 (Block 6)"
      }
    },
    {
      "id": "recpBU6PNSs22f5aX",
      "createdTime": "2025-08-26T22:41:49.000Z",
      "fields": {
        "absenceRequest": "TRUE - TRUE - PGY1-02 - 2026-04-11T00:00:00.000Z - 2026-05-06T00:00:00.000Z",
        "resident": [
          "rec6w0pOz3z54OaNH"
        ],
        "absenceId": "recpBU6PNSs22f5aX",
        "postGraduateYear": [
          "recBFlKB0nKMu8uqX"
        ],
        "residentId": [
          "rec6w0pOz3z54OaNH"
        ],
        "absenceStart": "2026-04-11",
        "absenceEnd": "2026-05-06",
        "absenceDuration": 26,
        "absenceApprovedResidency": true,
        "absenceApprovedArmy": true,
        "blockNumber": [
          "recukCPK15uxoCGtJ"
        ],
        "comments": "Imported from Excel: April 11 - May 6 (Block 11)"
      }
    },
    {
      "id": "recpgyduW8bzplVKT",
      "createdTime": "2025-08-06T22:11:29.000Z",
      "fields": {
        "absenceRequest": "TRUE - TRUE - PGY3-05 - 2025-11-29T00:00:00.000Z - 2025-12-05T00:00:00.000Z",
        "resident": [
          "recfCEd4ydvmWPMbq"
        ],
        "absenceId": "recpgyduW8bzplVKT",
        "postGraduateYear": [
          "recEWQHvAnrsTqGHO"
        ],
        "residentId": [
          "recfCEd4ydvmWPMbq"
        ],
        "absenceStart": "2025-11-29",
        "absenceEnd": "2025-12-05",
        "absenceDuration": 7,
        "absenceApprovedResidency": true,
        "absenceApprovedArmy": true,
        "blockNumber": [
          "recheHoNFIphdOOkc"
        ],
        "comments": "Leave"
      }
    },
    {
      "id": "recph5kZm5R2E5gWo",
      "createdTime": "2025-08-26T22:42:53.000Z",
      "fields": {
        "absenceRequest": "TRUE - TRUE - PGY1-05 - 2026-02-04T00:00:00.000Z - 2026-02-08T00:00:00.000Z",
        "resident": [
          "recdJZeXQjXmXhP4Q"
        ],
        "absenceId": "recph5kZm5R2E5gWo",
        "postGraduateYear": [
          "recBFlKB0nKMu8uqX"
        ],
        "residentId": [
          "recdJZeXQjXmXhP4Q"
        ],
        "absenceStart": "2026-02-04",
        "absenceEnd": "2026-02-08",
        "absenceDuration": 5,
        "absenceApprovedResidency": true,
        "absenceApprovedArmy": true,
        "blockNumber": [
          "recO8nXpj7mKdnOC2"
        ],
        "comments": "Imported from Excel: Feb 4 - 8 (Block 8)"
      }
    },
    {
      "id": "recpkec1cv64TK5E4",
      "createdTime": "2025-08-21T22:02:38.000Z",
      "fields": {
        "absenceRequest": "TRUE - TRUE - PGY2-03 - 2025-08-25T00:00:00.000Z - 2025-08-25T00:00:00.000Z",
        "resident": [
          "recEtslBYJpqYmdkd"
        ],
        "absenceId": "recpkec1cv64TK5E4",
        "postGraduateYear": [
          "rechgRuK16I8kTScb"
        ],
        "residentId": [
          "recEtslBYJpqYmdkd"
        ],
        "absenceStart": "2025-08-25",
        "absenceEnd": "2025-08-25",
        "absenceDuration": 1,
        "absenceApprovedResidency": true,
        "absenceApprovedArmy": true,
        "blockNumber": [
          "recba9vit0iwjDvyd"
        ],
        "comments": "7am\u201312pm & 12pm\u20135pm leave (full day)"
      }
    },
    {
      "id": "recqe5ZxpdMnrn5qi",
      "createdTime": "2025-08-07T00:14:25.000Z",
      "fields": {
        "absenceRequest": "TRUE - TRUE - PGY2-06 - 2025-10-31T00:00:00.000Z - 2025-10-31T00:00:00.000Z",
        "resident": [
          "recyynCFupNGxL9NK"
        ],
        "absenceId": "recqe5ZxpdMnrn5qi",
        "postGraduateYear": [
          "rechgRuK16I8kTScb"
        ],
        "residentId": [
          "recyynCFupNGxL9NK"
        ],
        "absenceStart": "2025-10-31",
        "absenceEnd": "2025-10-31",
        "absenceDuration": 1,
        "absenceApprovedResidency": true,
        "absenceApprovedArmy": true,
        "blockNumber": [
          "reciDYU7hTsmjgAaT"
        ],
        "comments": "Leave"
      }
    },
    {
      "id": "recrhACdgNbHaD36l",
      "createdTime": "2025-08-26T22:49:01.000Z",
      "fields": {
        "absenceRequest": "TRUE - TRUE - PGY3-05 - 2025-11-24T00:00:00.000Z - 2025-11-29T00:00:00.000Z",
        "resident": [
          "recfCEd4ydvmWPMbq"
        ],
        "absenceId": "recrhACdgNbHaD36l",
        "postGraduateYear": [
          "recEWQHvAnrsTqGHO"
        ],
        "residentId": [
          "recfCEd4ydvmWPMbq"
        ],
        "absenceStart": "2025-11-24",
        "absenceEnd": "2025-11-29",
        "absenceDuration": 6,
        "absenceApprovedResidency": true,
        "absenceApprovedArmy": true,
        "blockNumber": [
          "recheHoNFIphdOOkc"
        ],
        "comments": "Imported from Excel: Nov 24 - 29 (Block 6)"
      }
    },
    {
      "id": "recsFUB4SHBWdMNFM",
      "createdTime": "2025-08-26T22:46:05.000Z",
      "fields": {
        "absenceRequest": "TRUE - TRUE - PGY2-01 - 2025-07-13T00:00:00.000Z - 2025-07-14T00:00:00.000Z",
        "resident": [
          "rec3TityYwwXKG80J"
        ],
        "absenceId": "recsFUB4SHBWdMNFM",
        "postGraduateYear": [
          "rechgRuK16I8kTScb"
        ],
        "residentId": [
          "rec3TityYwwXKG80J"
        ],
        "absenceStart": "2025-07-13",
        "absenceEnd": "2025-07-14",
        "absenceDuration": 2,
        "absenceApprovedResidency": true,
        "absenceApprovedArmy": true,
        "blockNumber": [
          "recyCXLCOdygmwkaB"
        ],
        "comments": "Imported from Excel: July 13-14 (Block 1)"
      }
    },
    {
      "id": "recsJYvXFhlnMAW3E",
      "createdTime": "2025-10-14T21:58:56.000Z",
      "fields": {
        "absenceRequest": "TRUE - TRUE - PGY2-03 - 2026-01-10T00:00:00.000Z - 2026-01-21T00:00:00.000Z",
        "resident": [
          "recEtslBYJpqYmdkd"
        ],
        "absenceId": "recsJYvXFhlnMAW3E",
        "postGraduateYear": [
          "rechgRuK16I8kTScb"
        ],
        "residentId": [
          "recEtslBYJpqYmdkd"
        ],
        "absenceStart": "2026-01-10",
        "absenceEnd": "2026-01-21",
        "absenceDuration": 12,
        "absenceApprovedResidency": true,
        "absenceApprovedArmy": true,
        "blockNumber": [
          "rec4QEhUx2W3VpbJg",
          "recO8nXpj7mKdnOC2"
        ],
        "comments": "International Leave - Japan"
      }
    },
    {
      "id": "recsVIiHgk1YAWCvx",
      "createdTime": "2025-08-26T22:47:47.000Z",
      "fields": {
        "absenceRequest": "TRUE - TRUE - PGY3-03 - 2025-12-20T00:00:00.000Z - 2026-01-04T00:00:00.000Z",
        "resident": [
          "rec8tD8mJTRq51ewo"
        ],
        "absenceId": "recsVIiHgk1YAWCvx",
        "postGraduateYear": [
          "recEWQHvAnrsTqGHO"
        ],
        "residentId": [
          "rec8tD8mJTRq51ewo"
        ],
        "absenceStart": "2025-12-20",
        "absenceEnd": "2026-01-04",
        "absenceDuration": 16,
        "absenceApprovedResidency": true,
        "absenceApprovedArmy": true,
        "blockNumber": [
          "rec4QEhUx2W3VpbJg"
        ],
        "comments": "Imported from Excel: Dec 20 - Jan 4 (Block 7)"
      }
    },
    {
      "id": "recsiKy2oFXXjaO4z",
      "createdTime": "2025-08-26T22:43:43.000Z",
      "fields": {
        "absenceRequest": "TRUE - TRUE - PGY2-02 - 2026-03-21T00:00:00.000Z - 2026-03-23T00:00:00.000Z",
        "resident": [
          "recAtFCfEO8EjeJXh"
        ],
        "absenceId": "recsiKy2oFXXjaO4z",
        "postGraduateYear": [
          "rechgRuK16I8kTScb"
        ],
        "residentId": [
          "recAtFCfEO8EjeJXh"
        ],
        "absenceStart": "2026-03-21",
        "absenceEnd": "2026-03-23",
        "absenceDuration": 3,
        "absenceApprovedResidency": true,
        "absenceApprovedArmy": true,
        "blockNumber": [
          "recHQVwPtmZwHBnGx"
        ],
        "comments": "Imported from Excel: March 21 - 23 (Block 10)"
      }
    },
    {
      "id": "recskXqQU1nlVw2KB",
      "createdTime": "2025-08-06T22:05:40.000Z",
      "fields": {
        "absenceRequest": "TRUE - TRUE - PGY2-05 - 2025-11-24T00:00:00.000Z - 2025-11-30T00:00:00.000Z",
        "resident": [
          "recjkLHNGSlRaZA0R"
        ],
        "absenceId": "recskXqQU1nlVw2KB",
        "postGraduateYear": [
          "rechgRuK16I8kTScb"
        ],
        "residentId": [
          "recjkLHNGSlRaZA0R"
        ],
        "absenceStart": "2025-11-24",
        "absenceEnd": "2025-11-30",
        "absenceDuration": 7,
        "absenceApprovedResidency": true,
        "absenceApprovedArmy": true,
        "blockNumber": [
          "recheHoNFIphdOOkc"
        ],
        "comments": "Leave"
      }
    },
    {
      "id": "recterAsnjU3e2f99",
      "createdTime": "2025-07-14T22:31:21.000Z",
      "fields": {
        "absenceRequest": "TRUE - TRUE - PGY2-02 - 2025-07-31T00:00:00.000Z - 2025-08-06T00:00:00.000Z",
        "resident": [
          "recAtFCfEO8EjeJXh"
        ],
        "absenceId": "recterAsnjU3e2f99",
        "postGraduateYear": [
          "rechgRuK16I8kTScb"
        ],
        "residentId": [
          "recAtFCfEO8EjeJXh"
        ],
        "absenceStart": "2025-07-31",
        "absenceEnd": "2025-08-06",
        "absenceDuration": 7,
        "absenceApprovedResidency": true,
        "absenceApprovedArmy": true,
        "blockNumber": [
          "recba9vit0iwjDvyd"
        ],
        "comments": "Leave"
      }
    },
    {
      "id": "recwC37uLTTSKXwng",
      "createdTime": "2025-08-26T22:42:23.000Z",
      "fields": {
        "absenceRequest": "TRUE - TRUE - PGY1-03 - 2026-05-01T00:00:00.000Z - 2026-05-05T00:00:00.000Z",
        "resident": [
          "rec8sCH92dmDNq0Jy"
        ],
        "absenceId": "recwC37uLTTSKXwng",
        "postGraduateYear": [
          "recBFlKB0nKMu8uqX"
        ],
        "residentId": [
          "rec8sCH92dmDNq0Jy"
        ],
        "absenceStart": "2026-05-01",
        "absenceEnd": "2026-05-05",
        "absenceDuration": 5,
        "absenceApprovedResidency": true,
        "absenceApprovedArmy": true,
        "blockNumber": [
          "recukCPK15uxoCGtJ"
        ],
        "comments": "Imported from Excel: May 1-5"
      }
    },
    {
      "id": "recwSkc6m9snEIH8y",
      "createdTime": "2025-09-17T19:06:47.000Z",
      "fields": {
        "absenceRequest": "TRUE - TRUE - PGY2-04 - 2026-05-28T00:00:00.000Z - 2026-06-03T00:00:00.000Z",
        "resident": [
          "recSyteEOxDCJUCM1"
        ],
        "absenceId": "recwSkc6m9snEIH8y",
        "postGraduateYear": [
          "rechgRuK16I8kTScb"
        ],
        "residentId": [
          "recSyteEOxDCJUCM1"
        ],
        "absenceStart": "2026-05-28",
        "absenceEnd": "2026-06-03",
        "absenceDuration": 7,
        "absenceApprovedResidency": true,
        "absenceApprovedArmy": true,
        "blockNumber": [
          "rectoByFjGEhCHnP0"
        ],
        "comments": "Leave"
      }
    },
    {
      "id": "recwb0wjhFSEvnBrm",
      "createdTime": "2025-08-01T00:17:21.000Z",
      "fields": {
        "absenceRequest": "TRUE - TRUE - PGY3-03 - 2025-07-31T00:00:00.000Z - 2025-08-05T00:00:00.000Z",
        "resident": [
          "rec8tD8mJTRq51ewo"
        ],
        "absenceId": "recwb0wjhFSEvnBrm",
        "postGraduateYear": [
          "recEWQHvAnrsTqGHO"
        ],
        "residentId": [
          "rec8tD8mJTRq51ewo"
        ],
        "absenceStart": "2025-07-31",
        "absenceEnd": "2025-08-05",
        "absenceDuration": 6,
        "absenceApprovedResidency": true,
        "absenceApprovedArmy": true,
        "blockNumber": [
          "recba9vit0iwjDvyd"
        ],
        "comments": "Leave"
      }
    },
    {
      "id": "recyTFKmDj6lsxeKw",
      "createdTime": "2025-08-07T00:14:50.000Z",
      "fields": {
        "absenceRequest": "TRUE - TRUE - PGY2-06 - 2025-11-03T00:00:00.000Z - 2025-11-05T00:00:00.000Z",
        "resident": [
          "recyynCFupNGxL9NK"
        ],
        "absenceId": "recyTFKmDj6lsxeKw",
        "postGraduateYear": [
          "rechgRuK16I8kTScb"
        ],
        "residentId": [
          "recyynCFupNGxL9NK"
        ],
        "absenceStart": "2025-11-03",
        "absenceEnd": "2025-11-05",
        "absenceDuration": 3,
        "absenceApprovedResidency": true,
        "absenceApprovedArmy": true,
        "blockNumber": [
          "reciDYU7hTsmjgAaT"
        ],
        "comments": "Leave"
      }
    },
    {
      "id": "recyjP4PZQUOnOyTI",
      "createdTime": "2025-08-26T22:45:31.000Z",
      "fields": {
        "absenceRequest": "TRUE - TRUE - PGY2-05 - 2026-06-18T00:00:00.000Z - 2026-06-20T00:00:00.000Z",
        "resident": [
          "recjkLHNGSlRaZA0R"
        ],
        "absenceId": "recyjP4PZQUOnOyTI",
        "postGraduateYear": [
          "rechgRuK16I8kTScb"
        ],
        "residentId": [
          "recjkLHNGSlRaZA0R"
        ],
        "absenceStart": "2026-06-18",
        "absenceEnd": "2026-06-20",
        "absenceDuration": 3,
        "absenceApprovedResidency": true,
        "absenceApprovedArmy": true,
        "blockNumber": [
          "recWQEZ1WZ8lvXReP"
        ],
        "comments": "Imported from Excel: June 18 - 20"
      }
    },
    {
      "id": "recz7c8zId2sa6Exa",
      "createdTime": "2025-08-26T22:49:10.000Z",
      "fields": {
        "absenceRequest": "TRUE - TRUE -  - 2026-06-14T00:00:00.000Z - 2026-06-17T00:00:00.000Z",
        "absenceId": "recz7c8zId2sa6Exa",
        "absenceStart": "2026-06-14",
        "absenceEnd": "2026-06-17",
        "absenceDuration": 4,
        "absenceApprovedResidency": true,
        "absenceApprovedArmy": true,
        "blockNumber": [
          "recWQEZ1WZ8lvXReP"
        ],
        "comments": "Imported from Excel: June 14 - 17 (Block 13)"
      }
    }
  ]
}